treasure_image/__init__.py
treasure_image/__main__.py
treasure_image/converter.py
treasure_image/explorer.py
treasure_image/gif_maker.py
treasure_image/pirate.py
Treasure_Image-1.0.0.dist-info/METADATA
Treasure_Image-1.0.0.dist-info/WHEEL
Treasure_Image-1.0.0.dist-info/top_level.txt
Treasure_Image-1.0.0.dist-info/RECORD
