Metadata-Version: 2.1
Name: Treasure-Image
Version: 1.0.0
Summary: hide data(strings, images, files, scripts etc) into image, make gifs, covert images and files etc
Home-page: https://github.com/FatinShadab/TRREASURE_IMAGE
Author: Fatin Shadab
Author-email: fatinshadab123@gmail.com
License: MIT
Keywords: python,image,hide image,hide exe,image hack,converter,image converter,gifs
Platform: UNKNOWN
Classifier: License :: OSI Approved :: MIT License
Classifier: Programming Language :: Python :: 3.6
Classifier: Programming Language :: Python :: 3.7
Classifier: Programming Language :: Python :: 3.8
Classifier: Programming Language :: Python :: 3.9
Requires-Dist: Pillow
